cipher_jiachen_guov/__init__.py
cipher_jiachen_guov/cipher_jiachen_guov.py
cipher_jiachen_guov-0.0.1.dist-info/LICENSE
cipher_jiachen_guov-0.0.1.dist-info/WHEEL
cipher_jiachen_guov-0.0.1.dist-info/METADATA
cipher_jiachen_guov-0.0.1.dist-info/RECORD
