Metadata-Version: 2.1
Name: cipher-jiachen-guov
Version: 0.0.1
Summary: good
License: MIT
Author: Jiachen Guo
Requires-Python: >=3.8.12,<4.0.0
Classifier: License :: OSI Approved :: MIT License
Classifier: Programming Language :: Python :: 3
Classifier: Programming Language :: Python :: 3.10
Classifier: Programming Language :: Python :: 3.9
Requires-Dist: pandas (>=1.3.4,<2.0.0)
Requires-Dist: pytest (>=6.2.5,<7.0.0)
